mon2pcap/__init__.py
mon2pcap/common.py
mon2pcap/console.py
mon2pcap/constants.py
mon2pcap/errors.py
mon2pcap/helpers.py
mon2pcap/mon2pcap.py
mon2pcap/packets.py
mon2pcap-1.0.7.dist-info/LICENSE
mon2pcap-1.0.7.dist-info/METADATA
mon2pcap-1.0.7.dist-info/WHEEL
mon2pcap-1.0.7.dist-info/entry_points.txt
mon2pcap-1.0.7.dist-info/RECORD
