Metadata-Version: 2.1
Name: mon2pcap
Version: 1.0.7
Summary: Convert StarOS "monitor subscriber" or "monitor protocol" ASCII dump to PCAP
Home-page: https://github.com/arussu/mon2pcap
License: GPL-3.0-only
Keywords: scapy,mon2pcap
Author: Artur Russu
Author-email: arussu@cisco.com
Requires-Python: >=3.8.1,<4.0.0
Classifier: Intended Audience :: Telecommunications Industry
Classifier: License :: OSI Approved :: GNU General Public License v3 (GPLv3)
Classifier: Programming Language :: Python :: 3
Classifier: Programming Language :: Python :: 3.9
Classifier: Programming Language :: Python :: 3.10
Classifier: Programming Language :: Python :: 3.11
Classifier: Programming Language :: Python :: 3.8
Classifier: Topic :: System :: Networking
Requires-Dist: Jinja2 (>=3.1.2,<4.0.0)
Requires-Dist: scapy (>=2.5.0,<3.0.0)
Requires-Dist: tqdm (>=4.65.0,<5.0.0)
Project-URL: Repository, https://github.com/arussu/mon2pcap
